pure_math/__init__.py
pure_math-0.0.2.dist-info/METADATA
pure_math-0.0.2.dist-info/WHEEL
pure_math-0.0.2.dist-info/licenses/LICENSE
pure_math-0.0.2.dist-info/RECORD
